setup.py
circuit_transformer/__init__.py
circuit_transformer/model.py
circuit_transformer/tensorflow_transformer.py
circuit_transformer/utils.py
circuit_transformer.egg-info/PKG-INFO
circuit_transformer.egg-info/SOURCES.txt
circuit_transformer.egg-info/dependency_links.txt
circuit_transformer.egg-info/requires.txt
circuit_transformer.egg-info/top_level.txt
circuit_transformer/bin/abc
circuit_transformer/bin/abc.exe
circuit_transformer/bin/abc.rc
circuit_transformer/bin/aigtoaig
circuit_transformer/bin/aigtoaig.exe
tests/test_circuit_transformer.py